neotheicebird/__init__.py
neotheicebird-0.1.1.dist-info/DESCRIPTION.rst
neotheicebird-0.1.1.dist-info/METADATA
neotheicebird-0.1.1.dist-info/RECORD
neotheicebird-0.1.1.dist-info/WHEEL
neotheicebird-0.1.1.dist-info/metadata.json
neotheicebird-0.1.1.dist-info/top_level.txt
