Metadata-Version: 2.0
Name: neotheicebird
Version: 0.1.1
Summary: Its a package that describes me. Kinda like an about-me page. You can learn about me by installing the library and importing it.
Home-page: UNKNOWN
Author: Prashanth Gandhiraj
Author-email: neotheicebird@gmail.com
License: License
